odoo/addons/ssi_qr_code_mixin/README.rst
odoo/addons/ssi_qr_code_mixin/__init__.py
odoo/addons/ssi_qr_code_mixin/__manifest__.py
odoo/addons/ssi_qr_code_mixin/i18n/ssi_qr_code_mixin.pot
odoo/addons/ssi_qr_code_mixin/models/__init__.py
odoo/addons/ssi_qr_code_mixin/models/ir_model.py
odoo/addons/ssi_qr_code_mixin/models/mixin_qr_code.py
odoo/addons/ssi_qr_code_mixin/static/description/icon.png
odoo/addons/ssi_qr_code_mixin/templates/mixin_qr_code_templates.xml
odoo/addons/ssi_qr_code_mixin/views/ir_model_views.xml
odoo14_addon_ssi_qr_code_mixin-14.0.2.1.1.dist-info/METADATA
odoo14_addon_ssi_qr_code_mixin-14.0.2.1.1.dist-info/WHEEL
odoo14_addon_ssi_qr_code_mixin-14.0.2.1.1.dist-info/top_level.txt
odoo14_addon_ssi_qr_code_mixin-14.0.2.1.1.dist-info/RECORD
